heraut/__init__.py
heraut/coreUtils.py
heraut/listener.py
heraut/sender.py
heraut-0.0.1.dev1.dist-info/LICENSE
heraut-0.0.1.dev1.dist-info/METADATA
heraut-0.0.1.dev1.dist-info/WHEEL
heraut-0.0.1.dev1.dist-info/top_level.txt
heraut-0.0.1.dev1.dist-info/RECORD
