Metadata-Version: 2.1
Name: heraut
Version: 0.0.1.dev1
Summary: The herald of python message passing between threads and processes
Home-page: https://github.com/mkupperman/heraut
Author: Michael Kupperman
Author-email: kupperma@uw.edu
License: UNKNOWN
Project-URL: Bug Tracker, https://github.com/mkupperman/heraut/issues
Platform: UNKNOWN
Classifier: Development Status :: 3 - Alpha
Classifier: Programming Language :: Python :: 3
Classifier: Programming Language :: Python :: 3.6
Classifier: Programming Language :: Python :: 3.7
Classifier: Programming Language :: Python :: 3.8
Classifier: Programming Language :: Python :: 3.9
Classifier: License :: OSI Approved :: BSD License
Classifier: Operating System :: OS Independent
Requires-Python: >=3.6
Requires-Dist: watchdog (>=2.0.0)
